mussum_ipsun/__init__.py
mussum_ipsun/create.py
mussum_ipsun/generate_ipsum.py
mussum_ipsun-0.0.1.dist-info/METADATA
mussum_ipsun-0.0.1.dist-info/WHEEL
mussum_ipsun-0.0.1.dist-info/top_level.txt
mussum_ipsun-0.0.1.dist-info/RECORD
