Metadata-Version: 2.1
Name: mussum-ipsun
Version: 0.0.1
Summary: Mussum Ipsun generate.
Home-page: https://github.com/MarcianoPazinatto/mussum-ipsun-package.git
Author: MarkCiano
Author-email: marcianopazinatto@gmail.com
License: UNKNOWN
Platform: UNKNOWN
Requires-Python: >=3.10
